test/__init__.py
test/test_applicaiton_tags.py
test/test_client.py
test/test_direct.py
test/test_histogram_impl.py
test/test_proxy.py
test/test_wavefront_client.py
test/test_wavefront_metrics_registry.py
test/test_wavefront_python_sdk.py
wavefront_sdk/__init__.py
wavefront_sdk/client.py
wavefront_sdk/client_factory.py
wavefront_sdk/direct.py
wavefront_sdk/multi_clients.py
wavefront_sdk/proxy.py
wavefront_sdk/auth/__init__.py
wavefront_sdk/auth/csp/__init__.py
wavefront_sdk/auth/csp/authorize_response.py
wavefront_sdk/auth/csp/csp_request.py
wavefront_sdk/auth/csp/csp_token_service.py
wavefront_sdk/auth/csp/token_service.py
wavefront_sdk/auth/csp/token_service_factory.py
wavefront_sdk/common/__init__.py
wavefront_sdk/common/application_tags.py
wavefront_sdk/common/connection_handler.py
wavefront_sdk/common/constants.py
wavefront_sdk/common/heartbeater_service.py
wavefront_sdk/common/proxy_connection_handler.py
wavefront_sdk/common/utils.py
wavefront_sdk/common/metrics/__init__.py
wavefront_sdk/common/metrics/counter.py
wavefront_sdk/common/metrics/deltacounter.py
wavefront_sdk/common/metrics/gauge.py
wavefront_sdk/common/metrics/metrics.py
wavefront_sdk/common/metrics/registry.py
wavefront_sdk/entities/__init__.py
wavefront_sdk/entities/event/__init__.py
wavefront_sdk/entities/event/sender.py
wavefront_sdk/entities/histogram/__init__.py
wavefront_sdk/entities/histogram/histogram_granularity.py
wavefront_sdk/entities/histogram/histogram_impl.py
wavefront_sdk/entities/histogram/sender.py
wavefront_sdk/entities/metrics/__init__.py
wavefront_sdk/entities/metrics/sender.py
wavefront_sdk/entities/tracing/__init__.py
wavefront_sdk/entities/tracing/sender.py
wavefront_sdk/entities/tracing/span_log.py
wavefront_sdk_python-2.1.0.dist-info/LICENSE
wavefront_sdk_python-2.1.0.dist-info/METADATA
wavefront_sdk_python-2.1.0.dist-info/WHEEL
wavefront_sdk_python-2.1.0.dist-info/top_level.txt
wavefront_sdk_python-2.1.0.dist-info/RECORD
