Metadata-Version: 2.1
Name: wavefront-sdk-python
Version: 2.1.0
Summary: VMware Aria Operations for Applications Python SDK
Home-page: https://github.com/wavefrontHQ/wavefront-sdk-python
Author: VMware Aria Operations for Applications Team
License: Apache-2.0
Keywords: Aria,Aria Operations,Aria Operations for Applications,3D Observability,Distributed Tracing,Histograms,Logging,Metrics,Monitoring,Observability,Tracing,VMware Aria,VMware Aria Operations,VMware Aria Operations for Applications,Wavefront,Wavefront SDK
Classifier: Development Status :: 5 - Production/Stable
Classifier: Intended Audience :: Developers
Classifier: Intended Audience :: Information Technology
Classifier: Intended Audience :: System Administrators
Classifier: License :: OSI Approved :: Apache Software License
Classifier: Programming Language :: Python :: 3.8
Classifier: Programming Language :: Python :: 3.9
Classifier: Programming Language :: Python :: 3.10
Classifier: Programming Language :: Python :: 3.11
Classifier: Topic :: Software Development :: Libraries :: Python Modules
Classifier: Topic :: System :: Monitoring
Classifier: Topic :: System :: Networking :: Monitoring
License-File: LICENSE
Requires-Dist: requests >=2.27
Requires-Dist: tdigest >=0.5.2
Requires-Dist: Deprecated >=1.2.10
